showerdata/__init__.py
showerdata/__main__.py
showerdata/_version.py
showerdata/cluster_module.py
showerdata/core.py
showerdata/detector.py
showerdata/filter.py
showerdata/observables.py
showerdata/py.typed
showerdata/shift_showers.py
showerdata/shuffle.py
showerdata-0.6.1.dist-info/licenses/LICENSE
showerdata-0.6.1.dist-info/METADATA
showerdata-0.6.1.dist-info/WHEEL
showerdata-0.6.1.dist-info/entry_points.txt
showerdata-0.6.1.dist-info/top_level.txt
showerdata-0.6.1.dist-info/RECORD
