Metadata-Version: 2.4
Name: showerdata
Version: 0.6.1
Summary: A Python library for shower data handling
Author-email: Thorsten Buss <Thorsten.Buss@uni-hamburg.de>
License-Expression: MIT
Project-URL: Repository, https://github.com/FLC-QU-hep/ShowerData.git
Project-URL: Issues, https://github.com/FLC-QU-hep/ShowerData/issues
Project-URL: Documentation, https://flc-qu-hep.github.io/ShowerData/
Keywords: data,shower,hep,particle physics
Classifier: Intended Audience :: Developers
Classifier: Operating System :: OS Independent
Classifier: Programming Language :: Python :: 3
Classifier: Programming Language :: Python :: 3.10
Classifier: Programming Language :: Python :: 3.11
Classifier: Programming Language :: Python :: 3.12
Classifier: Programming Language :: Python :: 3.13
Classifier: Programming Language :: Python :: 3.14
Requires-Python: <4,>=3.10
License-File: LICENSE
Requires-Dist: numpy<3,>=2.1.0
Requires-Dist: h5py<4,>=3.11.0
Dynamic: license-file
